marzbanpy/__init__.py
marzbanpy/exceptions.py
marzbanpy/marzban.py
marzbanpy/marzban_response.py
marzbanpy/token.py
marzbanpy/enums/__init__.py
marzbanpy/enums/host.py
marzbanpy/enums/node.py
marzbanpy/enums/system.py
marzbanpy/enums/user.py
marzbanpy/types/__init__.py
marzbanpy/types/admin.py
marzbanpy/types/base.py
marzbanpy/types/hosts.py
marzbanpy/types/node.py
marzbanpy/types/user.py
marzbanpy/types/user_template.py
marzbanpy/utils/__init__.py
marzbanpy/utils/raise_exception.py
marzbanpy-1.5.2.dist-info/METADATA
marzbanpy-1.5.2.dist-info/WHEEL
marzbanpy-1.5.2.dist-info/licenses/LICENSE
marzbanpy-1.5.2.dist-info/RECORD
