Metadata-Version: 2.3
Name: marzbanpy
Version: 1.5.2
Summary: An unofficial library for marzban panel
Project-URL: Repository, https://github.com/gunsh1p/marzbanpy/
Author-email: Бертолло Виктор <bertollo.victor@gmail.com>
License: MIT License
License-File: LICENSE
Keywords: marzban,shadowsocks,trojan,vless,vmess,xray,xray-core,xtls
Requires-Python: >=3.10
Requires-Dist: httpx==0.27.0
Requires-Dist: pydantic==2.8.2
